{"moduleName":["Data","Enum","Gen"],"reExports":{},"imports":[{"annotation":{"meta":null,"sourceSpan":{"start":[1,1],"end":[18,18]}},"moduleName":["Control","Applicative"]},{"annotation":{"meta":null,"sourceSpan":{"start":[1,1],"end":[18,18]}},"moduleName":["Control","Monad","Gen"]},{"annotation":{"meta":null,"sourceSpan":{"start":[1,1],"end":[18,18]}},"moduleName":["Data","Bounded"]},{"annotation":{"meta":null,"sourceSpan":{"start":[1,1],"end":[18,18]}},"moduleName":["Data","Enum"]},{"annotation":{"meta":null,"sourceSpan":{"start":[1,1],"end":[18,18]}},"moduleName":["Data","Foldable"]},{"annotation":{"meta":null,"sourceSpan":{"start":[1,1],"end":[18,18]}},"moduleName":["Data","Maybe"]},{"annotation":{"meta":null,"sourceSpan":{"start":[1,1],"end":[18,18]}},"moduleName":["Data","NonEmpty"]},{"annotation":{"meta":null,"sourceSpan":{"start":[1,1],"end":[18,18]}},"moduleName":["Data","Unfoldable1"]},{"annotation":{"meta":null,"sourceSpan":{"start":[3,1],"end":[3,15]}},"moduleName":["Prelude"]},{"annotation":{"meta":null,"sourceSpan":{"start":[1,1],"end":[18,18]}},"moduleName":["Prim"]}],"builtWith":"0.14.4","modulePath":".spago/enums/v5.0.0/src/Data/Enum/Gen.purs","exports":["genBoundedEnum"],"decls":[{"annotation":{"meta":null,"sourceSpan":{"start":[11,1],"end":[11,65]}},"identifier":"genBoundedEnum","expression":{"annotation":{"meta":null,"sourceSpan":{"start":[11,1],"end":[11,65]}},"body":{"annotation":{"meta":null,"sourceSpan":{"start":[11,1],"end":[11,65]}},"body":{"annotation":{"meta":null,"sourceSpan":{"start":[13,3],"end":[18,18]}},"binds":[{"annotation":{"meta":null,"sourceSpan":{"start":[11,1],"end":[11,65]}},"identifier":"v","expression":{"annotation":{"meta":null,"sourceSpan":{"start":[13,8],"end":[13,19]}},"argument":{"annotation":{"meta":null,"sourceSpan":{"start":[13,8],"end":[13,19]}},"argument":{"annotation":{"meta":null,"sourceSpan":{"start":[13,8],"end":[13,19]}},"argument":{"annotation":{"meta":null,"sourceSpan":{"start":[0,0],"end":[0,0]}},"value":{"moduleName":["Prim"],"identifier":"undefined"},"type":"Var"},"type":"App","abstraction":{"annotation":{"meta":null,"sourceSpan":{"start":[13,8],"end":[13,19]}},"expression":{"annotation":{"meta":null,"sourceSpan":{"start":[0,0],"end":[0,0]}},"value":{"moduleName":null,"identifier":"dictBoundedEnum"},"type":"Var"},"fieldName":"Bounded0","type":"Accessor"}},"type":"App","abstraction":{"annotation":{"meta":{"metaType":"IsForeign"},"sourceSpan":{"start":[13,13],"end":[13,19]}},"value":{"moduleName":["Data","Bounded"],"identifier":"bottom"},"type":"Var"}},"type":"App","abstraction":{"annotation":{"meta":null,"sourceSpan":{"start":[13,8],"end":[13,19]}},"argument":{"annotation":{"meta":null,"sourceSpan":{"start":[13,8],"end":[13,19]}},"argument":{"annotation":{"meta":null,"sourceSpan":{"start":[0,0],"end":[0,0]}},"value":{"moduleName":["Prim"],"identifier":"undefined"},"type":"Var"},"type":"App","abstraction":{"annotation":{"meta":null,"sourceSpan":{"start":[13,8],"end":[13,19]}},"expression":{"annotation":{"meta":null,"sourceSpan":{"start":[0,0],"end":[0,0]}},"value":{"moduleName":null,"identifier":"dictBoundedEnum"},"type":"Var"},"fieldName":"Enum1","type":"Accessor"}},"type":"App","abstraction":{"annotation":{"meta":{"metaType":"IsForeign"},"sourceSpan":{"start":[13,8],"end":[13,12]}},"value":{"moduleName":["Data","Enum"],"identifier":"succ"},"type":"Var"}}},"bindType":"NonRec"}],"expression":{"annotation":{"meta":null,"sourceSpan":{"start":[13,3],"end":[18,18]}},"caseExpressions":[{"annotation":{"meta":null,"sourceSpan":{"start":[11,1],"end":[11,65]}},"value":{"moduleName":null,"identifier":"v"},"type":"Var"}],"caseAlternatives":[{"binders":[{"constructorName":{"moduleName":["Data","Maybe"],"identifier":"Just"},"annotation":{"meta":{"metaType":"IsConstructor","identifiers":["value0"],"constructorType":"SumType"},"sourceSpan":{"start":[14,5],"end":[14,11]}},"typeName":{"moduleName":["Data","Maybe"],"identifier":"Maybe"},"binders":[{"annotation":{"meta":null,"sourceSpan":{"start":[14,10],"end":[14,11]}},"identifier":"a","binderType":"VarBinder"}],"binderType":"ConstructorBinder"}],"expression":{"annotation":{"meta":null,"sourceSpan":{"start":[15,7],"end":[16,44]}},"binds":[{"annotation":{"meta":null,"sourceSpan":{"start":[15,11],"end":[15,54]}},"identifier":"possibilities","expression":{"annotation":{"meta":null,"sourceSpan":{"start":[15,27],"end":[15,43]}},"argument":{"annotation":{"meta":null,"sourceSpan":{"start":[15,27],"end":[15,43]}},"argument":{"annotation":{"meta":null,"sourceSpan":{"start":[15,27],"end":[15,43]}},"argument":{"annotation":{"meta":null,"sourceSpan":{"start":[0,0],"end":[0,0]}},"value":{"moduleName":["Prim"],"identifier":"undefined"},"type":"Var"},"type":"App","abstraction":{"annotation":{"meta":null,"sourceSpan":{"start":[15,27],"end":[15,43]}},"expression":{"annotation":{"meta":null,"sourceSpan":{"start":[0,0],"end":[0,0]}},"value":{"moduleName":null,"identifier":"dictBoundedEnum"},"type":"Var"},"fieldName":"Bounded0","type":"Accessor"}},"type":"App","abstraction":{"annotation":{"meta":{"metaType":"IsForeign"},"sourceSpan":{"start":[15,40],"end":[15,43]}},"value":{"moduleName":["Data","Bounded"],"identifier":"top"},"type":"Var"}},"type":"App","abstraction":{"annotation":{"meta":null,"sourceSpan":{"start":[15,27],"end":[15,39]}},"argument":{"annotation":{"meta":null,"sourceSpan":{"start":[15,38],"end":[15,39]}},"value":{"moduleName":null,"identifier":"a"},"type":"Var"},"type":"App","abstraction":{"annotation":{"meta":null,"sourceSpan":{"start":[15,27],"end":[15,39]}},"argument":{"annotation":{"meta":null,"sourceSpan":{"start":[0,0],"end":[0,0]}},"value":{"moduleName":["Data","Unfoldable1"],"identifier":"unfoldable1Array"},"type":"Var"},"type":"App","abstraction":{"annotation":{"meta":null,"sourceSpan":{"start":[15,27],"end":[15,39]}},"argument":{"annotation":{"meta":null,"sourceSpan":{"start":[15,27],"end":[15,39]}},"argument":{"annotation":{"meta":null,"sourceSpan":{"start":[0,0],"end":[0,0]}},"value":{"moduleName":["Prim"],"identifier":"undefined"},"type":"Var"},"type":"App","abstraction":{"annotation":{"meta":null,"sourceSpan":{"start":[15,27],"end":[15,39]}},"expression":{"annotation":{"meta":null,"sourceSpan":{"start":[0,0],"end":[0,0]}},"value":{"moduleName":null,"identifier":"dictBoundedEnum"},"type":"Var"},"fieldName":"Enum1","type":"Accessor"}},"type":"App","abstraction":{"annotation":{"meta":{"metaType":"IsForeign"},"sourceSpan":{"start":[15,27],"end":[15,37]}},"value":{"moduleName":["Data","Enum"],"identifier":"enumFromTo"},"type":"Var"}}}}},"bindType":"NonRec"}],"expression":{"annotation":{"meta":null,"sourceSpan":{"start":[16,10],"end":[16,44]}},"argument":{"annotation":{"meta":null,"sourceSpan":{"start":[16,20],"end":[16,43]}},"argument":{"annotation":{"meta":null,"sourceSpan":{"start":[16,30],"end":[16,43]}},"value":{"moduleName":null,"identifier":"possibilities"},"type":"Var"},"type":"App","abstraction":{"annotation":{"meta":null,"sourceSpan":{"start":[16,20],"end":[16,43]}},"argument":{"annotation":{"meta":null,"sourceSpan":{"start":[16,20],"end":[16,43]}},"argument":{"annotation":{"meta":null,"sourceSpan":{"start":[16,20],"end":[16,43]}},"argument":{"annotation":{"meta":null,"sourceSpan":{"start":[0,0],"end":[0,0]}},"value":{"moduleName":["Prim"],"identifier":"undefined"},"type":"Var"},"type":"App","abstraction":{"annotation":{"meta":null,"sourceSpan":{"start":[16,20],"end":[16,43]}},"expression":{"annotation":{"meta":null,"sourceSpan":{"start":[0,0],"end":[0,0]}},"value":{"moduleName":null,"identifier":"dictBoundedEnum"},"type":"Var"},"fieldName":"Bounded0","type":"Accessor"}},"type":"App","abstraction":{"annotation":{"meta":{"metaType":"IsForeign"},"sourceSpan":{"start":[16,20],"end":[16,26]}},"value":{"moduleName":["Data","Bounded"],"identifier":"bottom"},"type":"Var"}},"type":"App","abstraction":{"annotation":{"meta":{"metaType":"IsConstructor","identifiers":["value0","value1"],"constructorType":"ProductType"},"sourceSpan":{"start":[16,27],"end":[16,29]}},"value":{"moduleName":["Data","NonEmpty"],"identifier":"NonEmpty"},"type":"Var"}}},"type":"App","abstraction":{"annotation":{"meta":null,"sourceSpan":{"start":[16,10],"end":[16,44]}},"argument":{"annotation":{"meta":null,"sourceSpan":{"start":[16,10],"end":[16,44]}},"argument":{"annotation":{"meta":null,"sourceSpan":{"start":[0,0],"end":[0,0]}},"value":{"moduleName":["Data","Foldable"],"identifier":"foldableArray"},"type":"Var"},"type":"App","abstraction":{"annotation":{"meta":null,"sourceSpan":{"start":[0,0],"end":[0,0]}},"value":{"moduleName":["Data","NonEmpty"],"identifier":"foldable1NonEmpty"},"type":"Var"}},"type":"App","abstraction":{"annotation":{"meta":null,"sourceSpan":{"start":[16,10],"end":[16,44]}},"argument":{"annotation":{"meta":null,"sourceSpan":{"start":[0,0],"end":[0,0]}},"value":{"moduleName":null,"identifier":"dictMonadGen"},"type":"Var"},"type":"App","abstraction":{"annotation":{"meta":{"metaType":"IsForeign"},"sourceSpan":{"start":[16,10],"end":[16,18]}},"value":{"moduleName":["Control","Monad","Gen"],"identifier":"elements"},"type":"Var"}}}},"type":"Let"},"isGuarded":false},{"binders":[{"constructorName":{"moduleName":["Data","Maybe"],"identifier":"Nothing"},"annotation":{"meta":{"metaType":"IsConstructor","identifiers":[],"constructorType":"SumType"},"sourceSpan":{"start":[17,5],"end":[17,12]}},"typeName":{"moduleName":["Data","Maybe"],"identifier":"Maybe"},"binders":[],"binderType":"ConstructorBinder"}],"expression":{"annotation":{"meta":null,"sourceSpan":{"start":[18,7],"end":[18,18]}},"argument":{"annotation":{"meta":null,"sourceSpan":{"start":[18,7],"end":[18,18]}},"argument":{"annotation":{"meta":null,"sourceSpan":{"start":[18,7],"end":[18,18]}},"argument":{"annotation":{"meta":null,"sourceSpan":{"start":[0,0],"end":[0,0]}},"value":{"moduleName":["Prim"],"identifier":"undefined"},"type":"Var"},"type":"App","abstraction":{"annotation":{"meta":null,"sourceSpan":{"start":[18,7],"end":[18,18]}},"expression":{"annotation":{"meta":null,"sourceSpan":{"start":[0,0],"end":[0,0]}},"value":{"moduleName":null,"identifier":"dictBoundedEnum"},"type":"Var"},"fieldName":"Bounded0","type":"Accessor"}},"type":"App","abstraction":{"annotation":{"meta":{"metaType":"IsForeign"},"sourceSpan":{"start":[18,12],"end":[18,18]}},"value":{"moduleName":["Data","Bounded"],"identifier":"bottom"},"type":"Var"}},"type":"App","abstraction":{"annotation":{"meta":null,"sourceSpan":{"start":[18,7],"end":[18,18]}},"argument":{"annotation":{"meta":null,"sourceSpan":{"start":[18,7],"end":[18,18]}},"argument":{"annotation":{"meta":null,"sourceSpan":{"start":[0,0],"end":[0,0]}},"value":{"moduleName":["Prim"],"identifier":"undefined"},"type":"Var"},"type":"App","abstraction":{"annotation":{"meta":null,"sourceSpan":{"start":[18,7],"end":[18,18]}},"expression":{"annotation":{"meta":null,"sourceSpan":{"start":[18,7],"end":[18,18]}},"argument":{"annotation":{"meta":null,"sourceSpan":{"start":[0,0],"end":[0,0]}},"value":{"moduleName":["Prim"],"identifier":"undefined"},"type":"Var"},"type":"App","abstraction":{"annotation":{"meta":null,"sourceSpan":{"start":[18,7],"end":[18,18]}},"expression":{"annotation":{"meta":null,"sourceSpan":{"start":[0,0],"end":[0,0]}},"value":{"moduleName":null,"identifier":"dictMonadGen"},"type":"Var"},"fieldName":"Monad0","type":"Accessor"}},"fieldName":"Applicative0","type":"Accessor"}},"type":"App","abstraction":{"annotation":{"meta":{"metaType":"IsForeign"},"sourceSpan":{"start":[18,7],"end":[18,11]}},"value":{"moduleName":["Control","Applicative"],"identifier":"pure"},"type":"Var"}}},"isGuarded":false}],"type":"Case"},"type":"Let"},"argument":"dictBoundedEnum","type":"Abs"},"argument":"dictMonadGen","type":"Abs"},"bindType":"NonRec"}],"comments":[],"foreign":[],"sourceSpan":{"start":[1,1],"end":[18,18]}}