{"moduleName":["Data","Map","Gen"],"reExports":{},"imports":[{"annotation":{"meta":null,"sourceSpan":{"start":[1,1],"end":[24,53]}},"moduleName":["Control","Apply"]},{"annotation":{"meta":null,"sourceSpan":{"start":[1,1],"end":[24,53]}},"moduleName":["Control","Bind"]},{"annotation":{"meta":null,"sourceSpan":{"start":[1,1],"end":[24,53]}},"moduleName":["Control","Monad","Gen"]},{"annotation":{"meta":null,"sourceSpan":{"start":[1,1],"end":[24,53]}},"moduleName":["Control","Monad","Gen","Class"]},{"annotation":{"meta":null,"sourceSpan":{"start":[6,1],"end":[6,48]}},"moduleName":["Control","Monad","Rec","Class"]},{"annotation":{"meta":null,"sourceSpan":{"start":[1,1],"end":[24,53]}},"moduleName":["Data","Function"]},{"annotation":{"meta":null,"sourceSpan":{"start":[1,1],"end":[24,53]}},"moduleName":["Data","Functor"]},{"annotation":{"meta":null,"sourceSpan":{"start":[9,1],"end":[9,24]}},"moduleName":["Data","List"]},{"annotation":{"meta":null,"sourceSpan":{"start":[1,1],"end":[24,53]}},"moduleName":["Data","List","Types"]},{"annotation":{"meta":null,"sourceSpan":{"start":[7,1],"end":[7,36]}},"moduleName":["Data","Map"]},{"annotation":{"meta":null,"sourceSpan":{"start":[1,1],"end":[24,53]}},"moduleName":["Data","Map","Internal"]},{"annotation":{"meta":null,"sourceSpan":{"start":[1,1],"end":[24,53]}},"moduleName":["Data","Tuple"]},{"annotation":{"meta":null,"sourceSpan":{"start":[3,1],"end":[3,15]}},"moduleName":["Prelude"]},{"annotation":{"meta":null,"sourceSpan":{"start":[1,1],"end":[24,53]}},"moduleName":["Prim"]}],"builtWith":"0.14.4","modulePath":".spago/ordered-collections/v2.0.2/src/Data/Map/Gen.purs","exports":["genMap"],"decls":[{"annotation":{"meta":null,"sourceSpan":{"start":[12,1],"end":[19,17]}},"identifier":"genMap","expression":{"annotation":{"meta":null,"sourceSpan":{"start":[12,1],"end":[19,17]}},"body":{"annotation":{"meta":null,"sourceSpan":{"start":[12,1],"end":[19,17]}},"body":{"annotation":{"meta":null,"sourceSpan":{"start":[12,1],"end":[19,17]}},"body":{"annotation":{"meta":null,"sourceSpan":{"start":[12,1],"end":[19,17]}},"body":{"annotation":{"meta":null,"sourceSpan":{"start":[12,1],"end":[19,17]}},"body":{"annotation":{"meta":null,"sourceSpan":{"start":[20,26],"end":[24,53]}},"argument":{"annotation":{"meta":null,"sourceSpan":{"start":[20,32],"end":[24,53]}},"body":{"annotation":{"meta":null,"sourceSpan":{"start":[21,3],"end":[21,30]}},"argument":{"annotation":{"meta":null,"sourceSpan":{"start":[21,3],"end":[21,30]}},"body":{"annotation":{"meta":null,"sourceSpan":{"start":[22,3],"end":[24,53]}},"argument":{"annotation":{"meta":null,"sourceSpan":{"start":[22,3],"end":[24,53]}},"argument":{"annotation":{"meta":null,"sourceSpan":{"start":[24,11],"end":[24,53]}},"argument":{"annotation":{"meta":null,"sourceSpan":{"start":[24,23],"end":[24,52]}},"argument":{"annotation":{"meta":null,"sourceSpan":{"start":[24,44],"end":[24,52]}},"value":{"moduleName":null,"identifier":"genValue"},"type":"Var"},"type":"App","abstraction":{"annotation":{"meta":null,"sourceSpan":{"start":[24,23],"end":[24,52]}},"argument":{"annotation":{"meta":null,"sourceSpan":{"start":[24,23],"end":[24,52]}},"argument":{"annotation":{"meta":null,"sourceSpan":{"start":[24,33],"end":[24,39]}},"value":{"moduleName":null,"identifier":"genKey"},"type":"Var"},"type":"App","abstraction":{"annotation":{"meta":null,"sourceSpan":{"start":[24,23],"end":[24,52]}},"argument":{"annotation":{"meta":{"metaType":"IsConstructor","identifiers":["value0","value1"],"constructorType":"ProductType"},"sourceSpan":{"start":[24,23],"end":[24,28]}},"value":{"moduleName":["Data","Tuple"],"identifier":"Tuple"},"type":"Var"},"type":"App","abstraction":{"annotation":{"meta":null,"sourceSpan":{"start":[24,23],"end":[24,52]}},"argument":{"annotation":{"meta":null,"sourceSpan":{"start":[24,23],"end":[24,52]}},"argument":{"annotation":{"meta":null,"sourceSpan":{"start":[0,0],"end":[0,0]}},"value":{"moduleName":["Prim"],"identifier":"undefined"},"type":"Var"},"type":"App","abstraction":{"annotation":{"meta":null,"sourceSpan":{"start":[24,23],"end":[24,52]}},"expression":{"annotation":{"meta":null,"sourceSpan":{"start":[24,23],"end":[24,52]}},"argument":{"annotation":{"meta":null,"sourceSpan":{"start":[0,0],"end":[0,0]}},"value":{"moduleName":["Prim"],"identifier":"undefined"},"type":"Var"},"type":"App","abstraction":{"annotation":{"meta":null,"sourceSpan":{"start":[24,23],"end":[24,52]}},"expression":{"annotation":{"meta":null,"sourceSpan":{"start":[24,23],"end":[24,52]}},"argument":{"annotation":{"meta":null,"sourceSpan":{"start":[0,0],"end":[0,0]}},"value":{"moduleName":["Prim"],"identifier":"undefined"},"type":"Var"},"type":"App","abstraction":{"annotation":{"meta":null,"sourceSpan":{"start":[24,23],"end":[24,52]}},"expression":{"annotation":{"meta":null,"sourceSpan":{"start":[24,23],"end":[24,52]}},"argument":{"annotation":{"meta":null,"sourceSpan":{"start":[0,0],"end":[0,0]}},"value":{"moduleName":["Prim"],"identifier":"undefined"},"type":"Var"},"type":"App","abstraction":{"annotation":{"meta":null,"sourceSpan":{"start":[24,23],"end":[24,52]}},"expression":{"annotation":{"meta":null,"sourceSpan":{"start":[0,0],"end":[0,0]}},"value":{"moduleName":null,"identifier":"dictMonadGen"},"type":"Var"},"fieldName":"Monad0","type":"Accessor"}},"fieldName":"Bind1","type":"Accessor"}},"fieldName":"Apply0","type":"Accessor"}},"fieldName":"Functor0","type":"Accessor"}},"type":"App","abstraction":{"annotation":{"meta":{"metaType":"IsForeign"},"sourceSpan":{"start":[24,29],"end":[24,32]}},"value":{"moduleName":["Data","Functor"],"identifier":"map"},"type":"Var"}}}},"type":"App","abstraction":{"annotation":{"meta":null,"sourceSpan":{"start":[24,23],"end":[24,52]}},"argument":{"annotation":{"meta":null,"sourceSpan":{"start":[24,23],"end":[24,52]}},"argument":{"annotation":{"meta":null,"sourceSpan":{"start":[0,0],"end":[0,0]}},"value":{"moduleName":["Prim"],"identifier":"undefined"},"type":"Var"},"type":"App","abstraction":{"annotation":{"meta":null,"sourceSpan":{"start":[24,23],"end":[24,52]}},"expression":{"annotation":{"meta":null,"sourceSpan":{"start":[24,23],"end":[24,52]}},"argument":{"annotation":{"meta":null,"sourceSpan":{"start":[0,0],"end":[0,0]}},"value":{"moduleName":["Prim"],"identifier":"undefined"},"type":"Var"},"type":"App","abstraction":{"annotation":{"meta":null,"sourceSpan":{"start":[24,23],"end":[24,52]}},"expression":{"annotation":{"meta":null,"sourceSpan":{"start":[24,23],"end":[24,52]}},"argument":{"annotation":{"meta":null,"sourceSpan":{"start":[0,0],"end":[0,0]}},"value":{"moduleName":["Prim"],"identifier":"undefined"},"type":"Var"},"type":"App","abstraction":{"annotation":{"meta":null,"sourceSpan":{"start":[24,23],"end":[24,52]}},"expression":{"annotation":{"meta":null,"sourceSpan":{"start":[0,0],"end":[0,0]}},"value":{"moduleName":null,"identifier":"dictMonadGen"},"type":"Var"},"fieldName":"Monad0","type":"Accessor"}},"fieldName":"Bind1","type":"Accessor"}},"fieldName":"Apply0","type":"Accessor"}},"type":"App","abstraction":{"annotation":{"meta":{"metaType":"IsForeign"},"sourceSpan":{"start":[24,40],"end":[24,43]}},"value":{"moduleName":["Control","Apply"],"identifier":"apply"},"type":"Var"}}}},"type":"App","abstraction":{"annotation":{"meta":null,"sourceSpan":{"start":[24,11],"end":[24,53]}},"argument":{"annotation":{"meta":null,"sourceSpan":{"start":[0,0],"end":[0,0]}},"value":{"moduleName":["Data","List","Types"],"identifier":"unfoldableList"},"type":"Var"},"type":"App","abstraction":{"annotation":{"meta":null,"sourceSpan":{"start":[24,11],"end":[24,53]}},"argument":{"annotation":{"meta":null,"sourceSpan":{"start":[0,0],"end":[0,0]}},"value":{"moduleName":null,"identifier":"dictMonadGen"},"type":"Var"},"type":"App","abstraction":{"annotation":{"meta":null,"sourceSpan":{"start":[24,11],"end":[24,53]}},"argument":{"annotation":{"meta":null,"sourceSpan":{"start":[0,0],"end":[0,0]}},"value":{"moduleName":null,"identifier":"dictMonadRec"},"type":"Var"},"type":"App","abstraction":{"annotation":{"meta":{"metaType":"IsForeign"},"sourceSpan":{"start":[24,11],"end":[24,21]}},"value":{"moduleName":["Control","Monad","Gen"],"identifier":"unfoldable"},"type":"Var"}}}}},"type":"App","abstraction":{"annotation":{"meta":null,"sourceSpan":{"start":[22,3],"end":[24,53]}},"argument":{"annotation":{"meta":null,"sourceSpan":{"start":[23,6],"end":[23,18]}},"argument":{"annotation":{"meta":null,"sourceSpan":{"start":[0,0],"end":[0,0]}},"value":{"moduleName":["Data","List","Types"],"identifier":"foldableList"},"type":"Var"},"type":"App","abstraction":{"annotation":{"meta":null,"sourceSpan":{"start":[23,6],"end":[23,18]}},"argument":{"annotation":{"meta":null,"sourceSpan":{"start":[0,0],"end":[0,0]}},"value":{"moduleName":null,"identifier":"dictOrd"},"type":"Var"},"type":"App","abstraction":{"annotation":{"meta":{"metaType":"IsForeign"},"sourceSpan":{"start":[23,6],"end":[23,18]}},"value":{"moduleName":["Data","Map","Internal"],"identifier":"fromFoldable"},"type":"Var"}}},"type":"App","abstraction":{"annotation":{"meta":null,"sourceSpan":{"start":[22,3],"end":[24,53]}},"argument":{"annotation":{"meta":null,"sourceSpan":{"start":[22,3],"end":[24,53]}},"argument":{"annotation":{"meta":null,"sourceSpan":{"start":[0,0],"end":[0,0]}},"value":{"moduleName":["Prim"],"identifier":"undefined"},"type":"Var"},"type":"App","abstraction":{"annotation":{"meta":null,"sourceSpan":{"start":[22,3],"end":[24,53]}},"expression":{"annotation":{"meta":null,"sourceSpan":{"start":[22,3],"end":[24,53]}},"argument":{"annotation":{"meta":null,"sourceSpan":{"start":[0,0],"end":[0,0]}},"value":{"moduleName":["Prim"],"identifier":"undefined"},"type":"Var"},"type":"App","abstraction":{"annotation":{"meta":null,"sourceSpan":{"start":[22,3],"end":[24,53]}},"expression":{"annotation":{"meta":null,"sourceSpan":{"start":[22,3],"end":[24,53]}},"argument":{"annotation":{"meta":null,"sourceSpan":{"start":[0,0],"end":[0,0]}},"value":{"moduleName":["Prim"],"identifier":"undefined"},"type":"Var"},"type":"App","abstraction":{"annotation":{"meta":null,"sourceSpan":{"start":[22,3],"end":[24,53]}},"expression":{"annotation":{"meta":null,"sourceSpan":{"start":[22,3],"end":[24,53]}},"argument":{"annotation":{"meta":null,"sourceSpan":{"start":[0,0],"end":[0,0]}},"value":{"moduleName":["Prim"],"identifier":"undefined"},"type":"Var"},"type":"App","abstraction":{"annotation":{"meta":null,"sourceSpan":{"start":[22,3],"end":[24,53]}},"expression":{"annotation":{"meta":null,"sourceSpan":{"start":[0,0],"end":[0,0]}},"value":{"moduleName":null,"identifier":"dictMonadGen"},"type":"Var"},"fieldName":"Monad0","type":"Accessor"}},"fieldName":"Bind1","type":"Accessor"}},"fieldName":"Apply0","type":"Accessor"}},"fieldName":"Functor0","type":"Accessor"}},"type":"App","abstraction":{"annotation":{"meta":{"metaType":"IsForeign"},"sourceSpan":{"start":[24,7],"end":[24,10]}},"value":{"moduleName":["Data","Functor"],"identifier":"map"},"type":"Var"}}}},"type":"App","abstraction":{"annotation":{"meta":null,"sourceSpan":{"start":[22,3],"end":[24,53]}},"argument":{"annotation":{"meta":null,"sourceSpan":{"start":[22,3],"end":[22,25]}},"argument":{"annotation":{"meta":null,"sourceSpan":{"start":[22,11],"end":[22,24]}},"argument":{"annotation":{"meta":null,"sourceSpan":{"start":[22,17],"end":[22,24]}},"value":{"moduleName":null,"identifier":"newSize"},"type":"Var"},"type":"App","abstraction":{"annotation":{"meta":{"metaType":"IsForeign"},"sourceSpan":{"start":[22,11],"end":[22,16]}},"value":{"moduleName":["Data","Function"],"identifier":"const"},"type":"Var"}},"type":"App","abstraction":{"annotation":{"meta":null,"sourceSpan":{"start":[22,3],"end":[22,25]}},"argument":{"annotation":{"meta":null,"sourceSpan":{"start":[0,0],"end":[0,0]}},"value":{"moduleName":null,"identifier":"dictMonadGen"},"type":"Var"},"type":"App","abstraction":{"annotation":{"meta":{"metaType":"IsForeign"},"sourceSpan":{"start":[22,3],"end":[22,9]}},"value":{"moduleName":["Control","Monad","Gen","Class"],"identifier":"resize"},"type":"Var"}}},"type":"App","abstraction":{"annotation":{"meta":{"metaType":"IsForeign"},"sourceSpan":{"start":[22,26],"end":[22,27]}},"value":{"moduleName":["Data","Function"],"identifier":"apply"},"type":"Var"}}},"argument":"newSize","type":"Abs"},"type":"App","abstraction":{"annotation":{"meta":null,"sourceSpan":{"start":[21,3],"end":[21,30]}},"argument":{"annotation":{"meta":null,"sourceSpan":{"start":[21,14],"end":[21,30]}},"argument":{"annotation":{"meta":null,"sourceSpan":{"start":[21,26],"end":[21,30]}},"value":{"moduleName":null,"identifier":"size"},"type":"Var"},"type":"App","abstraction":{"annotation":{"meta":null,"sourceSpan":{"start":[21,14],"end":[21,25]}},"argument":{"annotation":{"meta":null,"sourceSpan":{"start":[21,24],"end":[21,25]}},"value":{"literalType":"IntLiteral","value":0},"type":"Literal"},"type":"App","abstraction":{"annotation":{"meta":null,"sourceSpan":{"start":[21,14],"end":[21,25]}},"argument":{"annotation":{"meta":null,"sourceSpan":{"start":[0,0],"end":[0,0]}},"value":{"moduleName":null,"identifier":"dictMonadGen"},"type":"Var"},"type":"App","abstraction":{"annotation":{"meta":{"metaType":"IsForeign"},"sourceSpan":{"start":[21,14],"end":[21,23]}},"value":{"moduleName":["Control","Monad","Gen","Class"],"identifier":"chooseInt"},"type":"Var"}}}},"type":"App","abstraction":{"annotation":{"meta":null,"sourceSpan":{"start":[21,3],"end":[21,30]}},"argument":{"annotation":{"meta":null,"sourceSpan":{"start":[21,3],"end":[21,30]}},"argument":{"annotation":{"meta":null,"sourceSpan":{"start":[0,0],"end":[0,0]}},"value":{"moduleName":["Prim"],"identifier":"undefined"},"type":"Var"},"type":"App","abstraction":{"annotation":{"meta":null,"sourceSpan":{"start":[21,3],"end":[21,30]}},"expression":{"annotation":{"meta":null,"sourceSpan":{"start":[21,3],"end":[21,30]}},"argument":{"annotation":{"meta":null,"sourceSpan":{"start":[0,0],"end":[0,0]}},"value":{"moduleName":["Prim"],"identifier":"undefined"},"type":"Var"},"type":"App","abstraction":{"annotation":{"meta":null,"sourceSpan":{"start":[21,3],"end":[21,30]}},"expression":{"annotation":{"meta":null,"sourceSpan":{"start":[0,0],"end":[0,0]}},"value":{"moduleName":null,"identifier":"dictMonadGen"},"type":"Var"},"fieldName":"Monad0","type":"Accessor"}},"fieldName":"Bind1","type":"Accessor"}},"type":"App","abstraction":{"annotation":{"meta":{"metaType":"IsForeign"},"sourceSpan":{"start":[21,3],"end":[21,30]}},"value":{"moduleName":["Control","Bind"],"identifier":"bind"},"type":"Var"}}}},"argument":"size","type":"Abs"},"type":"App","abstraction":{"annotation":{"meta":null,"sourceSpan":{"start":[20,26],"end":[24,53]}},"argument":{"annotation":{"meta":null,"sourceSpan":{"start":[0,0],"end":[0,0]}},"value":{"moduleName":null,"identifier":"dictMonadGen"},"type":"Var"},"type":"App","abstraction":{"annotation":{"meta":{"metaType":"IsForeign"},"sourceSpan":{"start":[20,26],"end":[20,31]}},"value":{"moduleName":["Control","Monad","Gen","Class"],"identifier":"sized"},"type":"Var"}}},"argument":"genValue","type":"Abs"},"argument":"genKey","type":"Abs"},"argument":"dictOrd","type":"Abs"},"argument":"dictMonadGen","type":"Abs"},"argument":"dictMonadRec","type":"Abs"},"bindType":"NonRec"}],"comments":[],"foreign":[],"sourceSpan":{"start":[1,1],"end":[24,53]}}