{"moduleName":["Data","Functor","Contravariant"],"reExports":{},"imports":[{"annotation":{"meta":null,"sourceSpan":{"start":[1,1],"end":[35,29]}},"moduleName":["Data","Const"]},{"annotation":{"meta":null,"sourceSpan":{"start":[1,1],"end":[35,29]}},"moduleName":["Data","Functor"]},{"annotation":{"meta":null,"sourceSpan":{"start":[1,1],"end":[35,29]}},"moduleName":["Data","Functor","Contravariant"]},{"annotation":{"meta":null,"sourceSpan":{"start":[1,1],"end":[35,29]}},"moduleName":["Data","Void"]},{"annotation":{"meta":null,"sourceSpan":{"start":[3,1],"end":[3,15]}},"moduleName":["Prelude"]},{"annotation":{"meta":null,"sourceSpan":{"start":[1,1],"end":[35,29]}},"moduleName":["Prim"]}],"builtWith":"0.14.4","modulePath":".spago/contravariant/v5.0.0/src/Data/Functor/Contravariant.purs","exports":["cmap","cmapFlipped","coerce","imapC","contravariantConst"],"decls":[{"annotation":{"meta":{"metaType":"IsTypeClassConstructor"},"sourceSpan":{"start":[16,1],"end":[17,45]}},"identifier":"Contravariant$Dict","expression":{"annotation":{"meta":{"metaType":"IsNewtype"},"sourceSpan":{"start":[16,1],"end":[17,45]}},"body":{"annotation":{"meta":null,"sourceSpan":{"start":[16,1],"end":[17,45]}},"value":{"moduleName":null,"identifier":"x"},"type":"Var"},"argument":"x","type":"Abs"},"bindType":"NonRec"},{"annotation":{"meta":null,"sourceSpan":{"start":[34,1],"end":[35,29]}},"identifier":"contravariantConst","expression":{"annotation":{"meta":null,"sourceSpan":{"start":[34,1],"end":[35,29]}},"argument":{"annotation":{"meta":null,"sourceSpan":{"start":[34,1],"end":[35,29]}},"value":{"literalType":"ObjectLiteral","value":[["cmap",{"annotation":{"meta":null,"sourceSpan":{"start":[34,1],"end":[35,29]}},"body":{"annotation":{"meta":null,"sourceSpan":{"start":[34,1],"end":[35,29]}},"body":{"annotation":{"meta":null,"sourceSpan":{"start":[34,1],"end":[35,29]}},"caseExpressions":[{"annotation":{"meta":null,"sourceSpan":{"start":[35,3],"end":[35,29]}},"value":{"moduleName":null,"identifier":"v"},"type":"Var"},{"annotation":{"meta":null,"sourceSpan":{"start":[35,3],"end":[35,29]}},"value":{"moduleName":null,"identifier":"v1"},"type":"Var"}],"caseAlternatives":[{"binders":[{"annotation":{"meta":null,"sourceSpan":{"start":[35,8],"end":[35,9]}},"binderType":"NullBinder"},{"constructorName":{"moduleName":["Data","Const"],"identifier":"Const"},"annotation":{"meta":{"metaType":"IsNewtype"},"sourceSpan":{"start":[35,11],"end":[35,18]}},"typeName":{"moduleName":["Data","Const"],"identifier":"Const"},"binders":[{"annotation":{"meta":null,"sourceSpan":{"start":[35,17],"end":[35,18]}},"identifier":"x","binderType":"VarBinder"}],"binderType":"ConstructorBinder"}],"expression":{"annotation":{"meta":null,"sourceSpan":{"start":[35,22],"end":[35,29]}},"argument":{"annotation":{"meta":null,"sourceSpan":{"start":[35,28],"end":[35,29]}},"value":{"moduleName":null,"identifier":"x"},"type":"Var"},"type":"App","abstraction":{"annotation":{"meta":{"metaType":"IsNewtype"},"sourceSpan":{"start":[35,22],"end":[35,27]}},"value":{"moduleName":["Data","Const"],"identifier":"Const"},"type":"Var"}},"isGuarded":false}],"type":"Case"},"argument":"v1","type":"Abs"},"argument":"v","type":"Abs"}]]},"type":"Literal"},"type":"App","abstraction":{"annotation":{"meta":{"metaType":"IsNewtype"},"sourceSpan":{"start":[34,1],"end":[35,29]}},"value":{"moduleName":["Data","Functor","Contravariant"],"identifier":"Contravariant$Dict"},"type":"Var"}},"bindType":"NonRec"},{"annotation":{"meta":null,"sourceSpan":{"start":[17,3],"end":[17,45]}},"identifier":"cmap","expression":{"annotation":{"meta":null,"sourceSpan":{"start":[17,3],"end":[17,45]}},"body":{"annotation":{"meta":null,"sourceSpan":{"start":[17,3],"end":[17,45]}},"caseExpressions":[{"annotation":{"meta":null,"sourceSpan":{"start":[17,3],"end":[17,45]}},"value":{"moduleName":null,"identifier":"dict"},"type":"Var"}],"caseAlternatives":[{"binders":[{"constructorName":{"moduleName":["Data","Functor","Contravariant"],"identifier":"Contravariant$Dict"},"annotation":{"meta":{"metaType":"IsNewtype"},"sourceSpan":{"start":[17,3],"end":[17,45]}},"typeName":{"moduleName":["Data","Functor","Contravariant"],"identifier":"Contravariant$Dict"},"binders":[{"annotation":{"meta":null,"sourceSpan":{"start":[17,3],"end":[17,45]}},"identifier":"v","binderType":"VarBinder"}],"binderType":"ConstructorBinder"}],"expression":{"annotation":{"meta":null,"sourceSpan":{"start":[17,3],"end":[17,45]}},"expression":{"annotation":{"meta":null,"sourceSpan":{"start":[17,3],"end":[17,45]}},"value":{"moduleName":null,"identifier":"v"},"type":"Var"},"fieldName":"cmap","type":"Accessor"},"isGuarded":false}],"type":"Case"},"argument":"dict","type":"Abs"},"bindType":"NonRec"},{"annotation":{"meta":null,"sourceSpan":{"start":[22,1],"end":[22,71]}},"identifier":"cmapFlipped","expression":{"annotation":{"meta":null,"sourceSpan":{"start":[22,1],"end":[22,71]}},"body":{"annotation":{"meta":null,"sourceSpan":{"start":[22,1],"end":[22,71]}},"body":{"annotation":{"meta":null,"sourceSpan":{"start":[22,1],"end":[22,71]}},"body":{"annotation":{"meta":null,"sourceSpan":{"start":[23,19],"end":[23,26]}},"argument":{"annotation":{"meta":null,"sourceSpan":{"start":[23,25],"end":[23,26]}},"value":{"moduleName":null,"identifier":"x"},"type":"Var"},"type":"App","abstraction":{"annotation":{"meta":null,"sourceSpan":{"start":[23,19],"end":[23,26]}},"argument":{"annotation":{"meta":null,"sourceSpan":{"start":[23,19],"end":[23,20]}},"value":{"moduleName":null,"identifier":"f"},"type":"Var"},"type":"App","abstraction":{"annotation":{"meta":null,"sourceSpan":{"start":[23,19],"end":[23,26]}},"argument":{"annotation":{"meta":null,"sourceSpan":{"start":[0,0],"end":[0,0]}},"value":{"moduleName":null,"identifier":"dictContravariant"},"type":"Var"},"type":"App","abstraction":{"annotation":{"meta":null,"sourceSpan":{"start":[23,21],"end":[23,24]}},"value":{"moduleName":["Data","Functor","Contravariant"],"identifier":"cmap"},"type":"Var"}}}},"argument":"f","type":"Abs"},"argument":"x","type":"Abs"},"argument":"dictContravariant","type":"Abs"},"bindType":"NonRec"},{"annotation":{"meta":null,"sourceSpan":{"start":[27,1],"end":[27,67]}},"identifier":"coerce","expression":{"annotation":{"meta":null,"sourceSpan":{"start":[27,1],"end":[27,67]}},"body":{"annotation":{"meta":null,"sourceSpan":{"start":[27,1],"end":[27,67]}},"body":{"annotation":{"meta":null,"sourceSpan":{"start":[27,1],"end":[27,67]}},"body":{"annotation":{"meta":null,"sourceSpan":{"start":[28,12],"end":[28,37]}},"argument":{"annotation":{"meta":null,"sourceSpan":{"start":[28,24],"end":[28,36]}},"argument":{"annotation":{"meta":null,"sourceSpan":{"start":[28,35],"end":[28,36]}},"value":{"moduleName":null,"identifier":"a"},"type":"Var"},"type":"App","abstraction":{"annotation":{"meta":null,"sourceSpan":{"start":[28,24],"end":[28,36]}},"argument":{"annotation":{"meta":{"metaType":"IsForeign"},"sourceSpan":{"start":[28,24],"end":[28,30]}},"value":{"moduleName":["Data","Void"],"identifier":"absurd"},"type":"Var"},"type":"App","abstraction":{"annotation":{"meta":null,"sourceSpan":{"start":[28,24],"end":[28,36]}},"argument":{"annotation":{"meta":null,"sourceSpan":{"start":[0,0],"end":[0,0]}},"value":{"moduleName":null,"identifier":"dictContravariant"},"type":"Var"},"type":"App","abstraction":{"annotation":{"meta":null,"sourceSpan":{"start":[28,31],"end":[28,34]}},"value":{"moduleName":["Data","Functor","Contravariant"],"identifier":"cmap"},"type":"Var"}}}},"type":"App","abstraction":{"annotation":{"meta":null,"sourceSpan":{"start":[28,12],"end":[28,37]}},"argument":{"annotation":{"meta":{"metaType":"IsForeign"},"sourceSpan":{"start":[28,12],"end":[28,18]}},"value":{"moduleName":["Data","Void"],"identifier":"absurd"},"type":"Var"},"type":"App","abstraction":{"annotation":{"meta":null,"sourceSpan":{"start":[28,12],"end":[28,37]}},"argument":{"annotation":{"meta":null,"sourceSpan":{"start":[0,0],"end":[0,0]}},"value":{"moduleName":null,"identifier":"dictFunctor"},"type":"Var"},"type":"App","abstraction":{"annotation":{"meta":{"metaType":"IsForeign"},"sourceSpan":{"start":[28,19],"end":[28,22]}},"value":{"moduleName":["Data","Functor"],"identifier":"map"},"type":"Var"}}}},"argument":"a","type":"Abs"},"argument":"dictFunctor","type":"Abs"},"argument":"dictContravariant","type":"Abs"},"bindType":"NonRec"},{"annotation":{"meta":null,"sourceSpan":{"start":[31,1],"end":[31,77]}},"identifier":"imapC","expression":{"annotation":{"meta":null,"sourceSpan":{"start":[31,1],"end":[31,77]}},"body":{"annotation":{"meta":null,"sourceSpan":{"start":[31,1],"end":[31,77]}},"body":{"annotation":{"meta":null,"sourceSpan":{"start":[31,1],"end":[31,77]}},"body":{"annotation":{"meta":null,"sourceSpan":{"start":[32,13],"end":[32,19]}},"argument":{"annotation":{"meta":null,"sourceSpan":{"start":[32,18],"end":[32,19]}},"value":{"moduleName":null,"identifier":"f"},"type":"Var"},"type":"App","abstraction":{"annotation":{"meta":null,"sourceSpan":{"start":[32,13],"end":[32,19]}},"argument":{"annotation":{"meta":null,"sourceSpan":{"start":[0,0],"end":[0,0]}},"value":{"moduleName":null,"identifier":"dictContravariant"},"type":"Var"},"type":"App","abstraction":{"annotation":{"meta":null,"sourceSpan":{"start":[32,13],"end":[32,17]}},"value":{"moduleName":["Data","Functor","Contravariant"],"identifier":"cmap"},"type":"Var"}}},"argument":"f","type":"Abs"},"argument":"v","type":"Abs"},"argument":"dictContravariant","type":"Abs"},"bindType":"NonRec"}],"comments":[],"foreign":[],"sourceSpan":{"start":[1,1],"end":[35,29]}}