{"moduleName":["Control","Category"],"reExports":{"Control.Semigroupoid":["compose"]},"imports":[{"annotation":{"meta":null,"sourceSpan":{"start":[1,1],"end":[21,17]}},"moduleName":["Control","Category"]},{"annotation":{"meta":null,"sourceSpan":{"start":[1,1],"end":[21,17]}},"moduleName":["Control","Semigroupoid"]},{"annotation":{"meta":null,"sourceSpan":{"start":[1,1],"end":[21,17]}},"moduleName":["Prim"]}],"builtWith":"0.14.4","modulePath":".spago/prelude/v5.0.1/src/Control/Category.purs","exports":["identity","categoryFn"],"decls":[{"annotation":{"meta":{"metaType":"IsTypeClassConstructor"},"sourceSpan":{"start":[17,1],"end":[18,30]}},"identifier":"Category$Dict","expression":{"annotation":{"meta":{"metaType":"IsNewtype"},"sourceSpan":{"start":[17,1],"end":[18,30]}},"body":{"annotation":{"meta":null,"sourceSpan":{"start":[17,1],"end":[18,30]}},"value":{"moduleName":null,"identifier":"x"},"type":"Var"},"argument":"x","type":"Abs"},"bindType":"NonRec"},{"annotation":{"meta":null,"sourceSpan":{"start":[18,3],"end":[18,30]}},"identifier":"identity","expression":{"annotation":{"meta":null,"sourceSpan":{"start":[18,3],"end":[18,30]}},"body":{"annotation":{"meta":null,"sourceSpan":{"start":[18,3],"end":[18,30]}},"caseExpressions":[{"annotation":{"meta":null,"sourceSpan":{"start":[18,3],"end":[18,30]}},"value":{"moduleName":null,"identifier":"dict"},"type":"Var"}],"caseAlternatives":[{"binders":[{"constructorName":{"moduleName":["Control","Category"],"identifier":"Category$Dict"},"annotation":{"meta":{"metaType":"IsNewtype"},"sourceSpan":{"start":[18,3],"end":[18,30]}},"typeName":{"moduleName":["Control","Category"],"identifier":"Category$Dict"},"binders":[{"annotation":{"meta":null,"sourceSpan":{"start":[18,3],"end":[18,30]}},"identifier":"v","binderType":"VarBinder"}],"binderType":"ConstructorBinder"}],"expression":{"annotation":{"meta":null,"sourceSpan":{"start":[18,3],"end":[18,30]}},"expression":{"annotation":{"meta":null,"sourceSpan":{"start":[18,3],"end":[18,30]}},"value":{"moduleName":null,"identifier":"v"},"type":"Var"},"fieldName":"identity","type":"Accessor"},"isGuarded":false}],"type":"Case"},"argument":"dict","type":"Abs"},"bindType":"NonRec"},{"annotation":{"meta":null,"sourceSpan":{"start":[20,1],"end":[21,17]}},"identifier":"categoryFn","expression":{"annotation":{"meta":null,"sourceSpan":{"start":[20,1],"end":[21,17]}},"argument":{"annotation":{"meta":null,"sourceSpan":{"start":[20,1],"end":[21,17]}},"value":{"literalType":"ObjectLiteral","value":[["identity",{"annotation":{"meta":null,"sourceSpan":{"start":[20,1],"end":[21,17]}},"body":{"annotation":{"meta":null,"sourceSpan":{"start":[21,16],"end":[21,17]}},"value":{"moduleName":null,"identifier":"x"},"type":"Var"},"argument":"x","type":"Abs"}],["Semigroupoid0",{"annotation":{"meta":null,"sourceSpan":{"start":[20,1],"end":[21,17]}},"body":{"annotation":{"meta":null,"sourceSpan":{"start":[0,0],"end":[0,0]}},"value":{"moduleName":["Control","Semigroupoid"],"identifier":"semigroupoidFn"},"type":"Var"},"argument":"$__unused","type":"Abs"}]]},"type":"Literal"},"type":"App","abstraction":{"annotation":{"meta":{"metaType":"IsNewtype"},"sourceSpan":{"start":[20,1],"end":[21,17]}},"value":{"moduleName":["Control","Category"],"identifier":"Category$Dict"},"type":"Var"}},"bindType":"NonRec"}],"comments":[],"foreign":[],"sourceSpan":{"start":[1,1],"end":[21,17]}}